amazon_mcp/__init__.py
amazon_mcp/server.py
iflow_mcp_amazon_mcp-0.1.13.dist-info/METADATA
iflow_mcp_amazon_mcp-0.1.13.dist-info/WHEEL
iflow_mcp_amazon_mcp-0.1.13.dist-info/entry_points.txt
iflow_mcp_amazon_mcp-0.1.13.dist-info/RECORD
