Metadata-Version: 2.4
Name: iflow-mcp_amazon-mcp
Version: 0.1.13
Summary: Amazon MCP server to search & buy across thousands of online stores
Author-email: Pol Alvarez <pol@fewsats.com>, Jordi Montes <jordi@fewsats.com>
Requires-Python: >=3.10
Requires-Dist: amazon-python>=0.0.11
Requires-Dist: mcp>=1.10.1
